python_mpesa_koros/__ init __.py
python_mpesa_koros/access_token.py
python_mpesa_koros/business_to_customer.py
python_mpesa_koros/customer_to_business.py
python_mpesa_koros/transaction_query.py
python_mpesa_koros/utils.py
python_mpesa_koros-0.1.7.dist-info/METADATA
python_mpesa_koros-0.1.7.dist-info/WHEEL
python_mpesa_koros-0.1.7.dist-info/top_level.txt
python_mpesa_koros-0.1.7.dist-info/RECORD
